logx/__init__.py
logx/compat/__init__.py
logx/compat/toml.py
logx/compat/yaml.py
logx/config/__init__.py
logx/config/configurator.py
logx/config/loaders.py
logx/types.py
logx/utils/__init__.py
logx/utils/factories.py
logx/utils/helpers.py
python_logx-0.1.1.dist-info/LICENSE
python_logx-0.1.1.dist-info/METADATA
python_logx-0.1.1.dist-info/WHEEL
python_logx-0.1.1.dist-info/RECORD
